package/playground.py
playground/__init__.py
playground/playground.py
playground_python-1.0.1.2.dist-info/LICENSE
playground_python-1.0.1.2.dist-info/METADATA
playground_python-1.0.1.2.dist-info/WHEEL
playground_python-1.0.1.2.dist-info/top_level.txt
playground_python-1.0.1.2.dist-info/RECORD
