Metadata-Version: 2.1
Name: playground-python
Version: 1.0.1.2
Home-page: https://github.com/BackGwa/Playground
Author: BACKGWA
Author-email: backgwa@icloud.com
License: BSD3
Requires-Python: >=3
License-File: LICENSE
